LICENCE.txt
MANIFEST.in
Profile_compute_student_per_school_stats.txt
Profile_compute_student_per_teacher_stats.txt
Profile_inp_get_districts_dataset.txt
Profile_inp_get_schools_dataset.txt
README.md
setup.py
test_students.py
.eggs/README.txt
.eggs/numpy-1.20.1-py3.9-win-amd64.egg/EGG-INFO/LICENSE.txt
.eggs/numpy-1.20.1-py3.9-win-amd64.egg/EGG-INFO/LICENSES_bundled.txt
.eggs/numpy-1.20.1-py3.9-win-amd64.egg/EGG-INFO/entry_points.txt
.eggs/numpy-1.20.1-py3.9-win-amd64.egg/EGG-INFO/top_level.txt
.eggs/numpy-1.20.1-py3.9-win-amd64.egg/numpy/LICENSE.txt
.eggs/numpy-1.20.1-py3.9-win-amd64.egg/numpy/__config__.py
.eggs/numpy-1.20.1-py3.9-win-amd64.egg/numpy/__init__.py
.eggs/numpy-1.20.1-py3.9-win-amd64.egg/numpy/_distributor_init.py
.eggs/numpy-1.20.1-py3.9-win-amd64.egg/numpy/_globals.py
.eggs/numpy-1.20.1-py3.9-win-amd64.egg/numpy/_pytesttester.py
.eggs/numpy-1.20.1-py3.9-win-amd64.egg/numpy/conftest.py
.eggs/numpy-1.20.1-py3.9-win-amd64.egg/numpy/ctypeslib.py
.eggs/numpy-1.20.1-py3.9-win-amd64.egg/numpy/dual.py
.eggs/numpy-1.20.1-py3.9-win-amd64.egg/numpy/matlib.py
.eggs/numpy-1.20.1-py3.9-win-amd64.egg/numpy/setup.py
.eggs/numpy-1.20.1-py3.9-win-amd64.egg/numpy/version.py
.eggs/numpy-1.20.1-py3.9-win-amd64.egg/numpy/compat/__init__.py
.eggs/numpy-1.20.1-py3.9-win-amd64.egg/numpy/compat/_inspect.py
.eggs/numpy-1.20.1-py3.9-win-amd64.egg/numpy/compat/py3k.py
.eggs/numpy-1.20.1-py3.9-win-amd64.egg/numpy/compat/setup.py
.eggs/numpy-1.20.1-py3.9-win-amd64.egg/numpy/compat/tests/__init__.py
.eggs/numpy-1.20.1-py3.9-win-amd64.egg/numpy/compat/tests/test_compat.py
.eggs/numpy-1.20.1-py3.9-win-amd64.egg/numpy/core/__init__.py
.eggs/numpy-1.20.1-py3.9-win-amd64.egg/numpy/core/_add_newdocs.py
.eggs/numpy-1.20.1-py3.9-win-amd64.egg/numpy/core/_add_newdocs_scalars.py
.eggs/numpy-1.20.1-py3.9-win-amd64.egg/numpy/core/_asarray.py
.eggs/numpy-1.20.1-py3.9-win-amd64.egg/numpy/core/_dtype.py
.eggs/numpy-1.20.1-py3.9-win-amd64.egg/numpy/core/_dtype_ctypes.py
.eggs/numpy-1.20.1-py3.9-win-amd64.egg/numpy/core/_exceptions.py
.eggs/numpy-1.20.1-py3.9-win-amd64.egg/numpy/core/_internal.py
.eggs/numpy-1.20.1-py3.9-win-amd64.egg/numpy/core/_methods.py
.eggs/numpy-1.20.1-py3.9-win-amd64.egg/numpy/core/_string_helpers.py
.eggs/pandas-1.2.2-py3.9-win-amd64.egg/EGG-INFO/entry_points.txt
.eggs/pandas-1.2.2-py3.9-win-amd64.egg/EGG-INFO/requires.txt
.eggs/pandas-1.2.2-py3.9-win-amd64.egg/EGG-INFO/top_level.txt
.eggs/python_dateutil-2.8.1-py3.9.egg/EGG-INFO/requires.txt
.eggs/python_dateutil-2.8.1-py3.9.egg/EGG-INFO/top_level.txt
.eggs/pytz-2021.1-py3.9.egg/EGG-INFO/LICENSE.txt
.eggs/pytz-2021.1-py3.9.egg/EGG-INFO/top_level.txt
python_da_final_vkaul.egg-info/PKG-INFO
python_da_final_vkaul.egg-info/SOURCES.txt
python_da_final_vkaul.egg-info/dependency_links.txt
python_da_final_vkaul.egg-info/top_level.txt