Metadata-Version: 2.1
Name: python-da-final-vkaul
Version: 0.0.1
Summary: Package computes specific statistics of students in Poland
Home-page: https://gitlab.uw.edu.pl/v.kaul/pythonda_finalassignment.git
Author: Vibhesh Kaul
Author-email: v.kaul@student.uw.edu.pl
License: UNKNOWN
Platform: UNKNOWN
Classifier: Programming Language :: Python :: 3
Classifier: License :: OSI Approved :: MIT License
Classifier: Operating System :: OS Independent
Requires-Python: >=3.6
